SpotifyUtil/SpotifyUtil.py
SpotifyUtil/__init__.py
SpotifyUtil/config.py
SpotifyUtil/file_reader.py
SpotifyUtil/secret.py
SpotifyUtil/utilityTest.py
SpotifyUtil-0.0.10.dist-info/LICENSE
SpotifyUtil-0.0.10.dist-info/METADATA
SpotifyUtil-0.0.10.dist-info/WHEEL
SpotifyUtil-0.0.10.dist-info/top_level.txt
SpotifyUtil-0.0.10.dist-info/RECORD
