Metadata-Version: 2.1
Name: SpotifyUtil
Version: 0.0.10
Summary: SpotifyUtils is a very useful library made over Spotipy to automate some rather tiring tasks.
Home-page: https://github.com/Arg0naut18/SpotifyUtil
Author: Arg0naut18
Author-email: Arg0naut18 <gaming.genos1729@gmail.com>
Project-URL: Homepage, https://github.com/Arg0naut18/SpotifyUtil
Keywords: Spotify,Spotipy,SpotifyUtil,SpotifyUtils
Classifier: Programming Language :: Python :: 3
Classifier: Development Status :: 3 - Alpha
Classifier: License :: OSI Approved :: GNU General Public License v3 (GPLv3)
Classifier: Operating System :: OS Independent
Requires-Python: >= 3.8
License-File: LICENSE
Requires-Dist: spotipy
